contentratings/README.rst
contentratings/__init__.py
contentratings/bbb.py
contentratings/category.py
contentratings/configure.zcml
contentratings/events.py
contentratings/interfaces.py
contentratings/meta.zcml
contentratings/metaconfigure.py
contentratings/metadirectives.py
contentratings/migrations.py
contentratings/permissions.py
contentratings/permissions.zcml
contentratings/rating.py
contentratings/storage.py
contentratings/usei18ndude.sh
contentratings/browser/__init__.py
contentratings/browser/aggregator.py
contentratings/browser/aggregator.txt
contentratings/browser/base_vocabs.py
contentratings/browser/basic.py
contentratings/browser/configure.zcml
contentratings/browser/editor_stars.pt
contentratings/browser/editor_stars_read.pt
contentratings/browser/interfaces.py
contentratings/browser/stars.pt
contentratings/browser/stars_view.pt
contentratings/browser/tests.py
contentratings/browser/traverser.py
contentratings/browser/utils.py
contentratings/browser/views.txt
contentratings/browser/bbb/__init__.py
contentratings/browser/bbb/configure.zcml
contentratings/browser/bbb/editor_rating.pt
contentratings/browser/bbb/editor_rating_edit.pt
contentratings/browser/bbb/interfaces.py
contentratings/browser/bbb/small_gray_star.gif
contentratings/browser/bbb/small_yellow_star.gif
contentratings/browser/bbb/user_rating.pt
contentratings/browser/bbb/user_rating_edit.pt
contentratings/browser/resources/X_icon_10x10.gif
contentratings/browser/resources/X_icon_10x10_gray.gif
contentratings/browser/resources/X_icon_20x20.gif
contentratings/browser/resources/X_icon_20x20_gray.gif
contentratings/browser/resources/cross.gif
contentratings/browser/resources/cross_grey.gif
contentratings/browser/resources/cross_small.gif
contentratings/browser/resources/cross_small_grey.gif
contentratings/browser/resources/star.gif
contentratings/browser/resources/star_rating.css
contentratings/browser/resources/star_small.gif
contentratings/locales/contentratings.pot
nti.contentratings-1.2.0.dist-info/COPYING.txt
nti.contentratings-1.2.0.dist-info/LICENSE
nti.contentratings-1.2.0.dist-info/METADATA
nti.contentratings-1.2.0.dist-info/WHEEL
nti.contentratings-1.2.0.dist-info/top_level.txt
nti.contentratings-1.2.0.dist-info/RECORD
