Metadata-Version: 2.1
Name: nti.contentratings
Version: 1.2.0
Summary: A small Zope 3 package (which also works with Zope 2.10+ and Five) that allows you to attach ratings to content.
Home-page: https://github.com/NextThought/nti.contentratings
Author: Alec Mitchell
Author-email: apm13@columbia.edu
License: ZPL
Keywords: ratings zope plone zope3
Platform: UNKNOWN
Classifier: Intended Audience :: Developers
Classifier: License :: OSI Approved :: Zope Public License
Classifier: Programming Language :: Python
Classifier: Programming Language :: Python :: 2.7
Classifier: Programming Language :: Python :: 3.6
Classifier: Programming Language :: Python :: 3.7
Classifier: Programming Language :: Python :: 3.8
Classifier: Programming Language :: Python :: 3.9
Classifier: Programming Language :: Python :: Implementation :: CPython
Classifier: Programming Language :: Python :: Implementation :: PyPy
Classifier: Framework :: Zope3
Classifier: Framework :: Zope2
Classifier: Framework :: Plone
Classifier: Framework :: Plone :: 4.0
Classifier: Framework :: Plone :: 4.1
Classifier: Framework :: Plone :: 4.2
Classifier: Framework :: Plone :: 4.3
Classifier: Framework :: Plone :: 5.0
Classifier: Framework :: Plone :: 5.1
Classifier: Topic :: Software Development :: Libraries :: Python Modules
Requires-Dist: setuptools
Requires-Dist: zope.component (>=5)
Requires-Dist: zope.componentvocabulary
Requires-Dist: zope.container
Requires-Dist: BTrees
Requires-Dist: zope.lifecycleevent
Requires-Dist: persistent
Requires-Dist: zope.schema
Requires-Dist: zope.traversing
Requires-Dist: zope.deferredimport
Requires-Dist: zope.annotation
Requires-Dist: zope.configuration
Requires-Dist: zope.tales
Requires-Dist: Acquisition
Provides-Extra: test
Requires-Dist: zope.testing ; extra == 'test'
Requires-Dist: zope.testrunner ; extra == 'test'
Requires-Dist: zope.app.testing ; extra == 'test'
Requires-Dist: coverage ; extra == 'test'
Provides-Extra: zope3
Requires-Dist: zope.app.content ; extra == 'zope3'
